{
    "productos": [
        {
            "name": "Product-one",
            "brand": "Mercedes-Benz",
            "model": "AMG a45s",
            "photo": "",
            "price": 64.725,
            "fuel": "gasolina",
            "traction": "4matic",
            "bodywork": "compacto",
            "consumption": "6.7l",
            "power": "225kw + 10Kw ~ (306Cv + 14Cv)"
        },
        {
            "name": "Product-two",
            "brand": "Mercedes-Benz",
            "model": "Clase C",
            "photo": "",
            "price": 50.972,
            "fuel": "Diesel",
            "traction": "trasera",
            "bodywork": "berlina",
            "consumption": "4.6l",
            "power": "120KW + 20KW (163Cv + 28Cv)"
        },
        {
            "name": "Product-three",
            "brand": "Mercedes-Benz",
            "model": "Clase E",
            "photo": "",
            "price": 56.947,
            "fuel": "Hibrido",
            "traction": "trasera",
            "bodywork": "berlina",
            "consumption": "4.8l",
            "power": "147Kw + 15KW (200Cv + 20Cv)"
        },
        {
            "name": "Product-four",
            "brand": "Mercedes-Benz",
            "model": "GLC Coupé",
            "photo": "",
            "price": 64.125,
            "fuel": "Hibrido",
            "traction": "integral",
            "bodywork": "suv",
            "consumption": "7.9l 20Kw",
            "power": "150Kw + 100KW (204Cv + 136Cv)"
        },
        {
            "name": "Product-six",
            "brand": "Mercedes-Benz",
            "model": "AMG GT",
            "photo": "url_de_la_imagen",
            "price": 150000,
            "fuel": "Gasolina",
            "traction": "Trasera",
            "bodywork": "Coupé",
            "consumption": "10 l/100km",
            "power": "350KW (476Cv)"
        },
        {
            "name": "Product-seven",
            "brand": "Nissan",
            "model": "GT-R",
            "photo": "url_de_la_imagen",
            "price": 120000,
            "fuel": "Gasolina",
            "traction": "Integral",
            "bodywork": "Coupé",
            "consumption": "12 l/100km",
            "power": "419KW (570Cv)"
        },
        {
            "name": "Product-eighth",
            "brand": "Ford",
            "model": "Mustang Shelby GT500",
            "photo": "url_de_la_imagen",
            "price": 90000,
            "fuel": "Gasolina",
            "traction": "Trasera",
            "bodywork": "Coupé",
            "consumption": "15 l/100km",
            "power": "567KW (770Cv)"
        },
        {
            "name": "Product-nine",
            "brand": "Mercedes-Benz",
            "model": "C63 AMG",
            "photo": "url_de_la_imagen",
            "price": 85000,
            "fuel": "Gasolina",
            "traction": "Trasera",
            "bodywork": "Berlina",
            "consumption": "11 l/100km",
            "power": "375KW (510Cv)"
        },
        {
            "name": "Product-ten",
            "brand": "Nissan",
            "model": "370Z Nismo",
            "photo": "url_de_la_imagen",
            "price": 55000,
            "fuel": "Gasolina",
            "traction": "Trasera",
            "bodywork": "Coupé",
            "consumption": "9 l/100km",
            "power": "261KW (355Cv)"
        },
        {
            "name": "Product-eleven",
            "brand": "Mercedes-Benz",
            "model": "AMG A45 S",
            "photo": "url_de_la_imagen",
            "price": 60000,
            "fuel": "Gasolina",
            "traction": "Integral",
            "bodywork": "Hatchback",
            "consumption": "8 l/100km",
            "power": "310KW (421Cv)"
        },
        {
            "name": "Product-twelve",
            "brand": "Nissan",
            "model": "370Z Heritage Edition",
            "photo": "url_de_la_imagen",
            "price": 48000,
            "fuel": "Gasolina",
            "traction": "Trasera",
            "bodywork": "Coupé",
            "consumption": "10 l/100km",
            "power": "257KW (350Cv)"
        },
        {
            "name": "Product-thirteen",
            "brand": "Ford",
            "model": "Focus RS",
            "photo": "url_de_la_imagen",
            "price": 40000,
            "fuel": "Gasolina",
            "traction": "Integral",
            "bodywork": "Hatchback",
            "consumption": "9 l/100km",
            "power": "257KW (350Cv)"
        },
        {
            "name": "Product-fourteen",
            "brand": "Mercedes-Benz",
            "model": "CLA 45 AMG",
            "photo": "url_de_la_imagen",
            "price": 70000,
            "fuel": "Gasolina",
            "traction": "Integral",
            "bodywork": "Coupé",
            "consumption": "9 l/100km",
            "power": "310KW (421Cv)"
        },
        {
            "name": "Product-fifteen",
            "brand": "Nissan",
            "model": "Nissan GT-R Nismo",
            "photo": "url_de_la_imagen",
            "price": 200000,
            "fuel": "Gasolina",
            "traction": "Integral",
            "bodywork": "Coupé",
            "consumption": "12 l/100km",
            "power": "441KW (600Cv)"
        },
        {
            "name": "Product-sixteen",
            "brand": "Ford",
            "model": "Ford GT",
            "photo": "url_de_la_imagen",
            "price": 500000,
            "fuel": "Gasolina",
            "traction": "Trasera",
            "bodywork": "Coupé",
            "consumption": "14 l/100km",
            "power": "482KW (656Cv)"
        },
        {
            "name": "Product-seventeen",
            "brand": "Mercedes-Benz",
            "model": "E63 AMG",
            "photo": "url_de_la_imagen",
            "price": 95000,
            "fuel": "Gasolina",
            "traction": "Integral",
            "bodywork": "Berlina",
            "consumption": "11 l/100km",
            "power": "420KW (571Cv)"
        },
        {
            "name": "Product-eighteen",
            "brand": "Nissan",
            "model": "Nissan 400Z",
            "photo": "url_de_la_imagen",
            "price": 45000,
            "fuel": "Gasolina",
            "traction": "Trasera",
            "bodywork": "Coupé",
            "consumption": "9 l/100km",
            "power": "294KW (400Cv)"
        },
        {
            "name": "Product-nineteen",
            "brand": "Ford",
            "model": "Mustang Mach 1",
            "photo": "url_de_la_imagen",
            "price": 60000,
            "fuel": "Gasolina",
            "traction": "Trasera",
            "bodywork": "Coupé",
            "consumption": "12 l/100km",
            "power": "358KW (487Cv)"
        },
        {
            "name": "Product-twenty",
            "brand": "Mercedes-Benz",
            "model": "S63 AMG",
            "photo": "url_de_la_imagen",
            "price": 150000,
            "fuel": "Gasolina",
            "traction": "Integral",
            "bodywork": "Berlina",
            "consumption": "13 l/100km",
            "power": "450KW (612Cv)"
        }
    ]
}